notanorm/__init__.py
notanorm/base.py
notanorm/connparse.py
notanorm/ddl_helper.py
notanorm/errors.py
notanorm/evil_open.py
notanorm/jsondb.py
notanorm/model.py
notanorm/modelx.py
notanorm/mysql.py
notanorm/pysql.py
notanorm/sqlite.py
notanorm-3.9.2.dist-info/LICENSE
notanorm-3.9.2.dist-info/METADATA
notanorm-3.9.2.dist-info/WHEEL
notanorm-3.9.2.dist-info/top_level.txt
notanorm-3.9.2.dist-info/RECORD
