Metadata-Version: 2.1
Name: notanorm
Version: 3.9.2
Summary: DB wrapper library
Home-page: https://github.com/AtakamaLLC/notanorm
Classifier: Development Status :: 5 - Production/Stable
Classifier: Intended Audience :: Developers
Classifier: License :: OSI Approved :: MIT License
Classifier: Operating System :: MacOS
Classifier: Operating System :: Microsoft :: Windows
Classifier: Operating System :: POSIX
Classifier: Programming Language :: Python :: 3
Classifier: Topic :: Software Development
Classifier: Topic :: Utilities
License-File: LICENSE
